LICENSE
MANIFEST.in
README.md
requirements.txt
requirements_dev.txt
setup.py
mljar_supervised.egg-info/PKG-INFO
mljar_supervised.egg-info/SOURCES.txt
mljar_supervised.egg-info/dependency_links.txt
mljar_supervised.egg-info/requires.txt
mljar_supervised.egg-info/top_level.txt
supervised/__init__.py
supervised/automl.py
supervised/base_automl.py
supervised/ensemble.py
supervised/exceptions.py
supervised/model_framework.py
supervised/algorithms/__init__.py
supervised/algorithms/algorithm.py
supervised/algorithms/baseline.py
supervised/algorithms/catboost.py
supervised/algorithms/decision_tree.py
supervised/algorithms/extra_trees.py
supervised/algorithms/factory.py
supervised/algorithms/knn.py
supervised/algorithms/lightgbm.py
supervised/algorithms/linear.py
supervised/algorithms/nn.py
supervised/algorithms/random_forest.py
supervised/algorithms/registry.py
supervised/algorithms/sklearn.py
supervised/algorithms/xgboost.py
supervised/callbacks/__init__.py
supervised/callbacks/callback.py
supervised/callbacks/callback_list.py
supervised/callbacks/early_stopping.py
supervised/callbacks/learner_time_constraint.py
supervised/callbacks/max_iters_constraint.py
supervised/callbacks/metric_logger.py
supervised/callbacks/terminate_on_nan.py
supervised/callbacks/total_time_constraint.py
supervised/fairness/__init__.py
supervised/fairness/metrics.py
supervised/fairness/optimization.py
supervised/fairness/plots.py
supervised/fairness/report.py
supervised/fairness/utils.py
supervised/preprocessing/__init__.py
supervised/preprocessing/datetime_transformer.py
supervised/preprocessing/encoding_selector.py
supervised/preprocessing/exclude_missing_target.py
supervised/preprocessing/goldenfeatures_transformer.py
supervised/preprocessing/kmeans_transformer.py
supervised/preprocessing/label_binarizer.py
supervised/preprocessing/label_encoder.py
supervised/preprocessing/preprocessing.py
supervised/preprocessing/preprocessing_categorical.py
supervised/preprocessing/preprocessing_missing.py
supervised/preprocessing/preprocessing_utils.py
supervised/preprocessing/scale.py
supervised/preprocessing/text_transformer.py
supervised/tuner/__init__.py
supervised/tuner/data_info.py
