Metadata-Version: 2.1
Name: mljar-supervised
Version: 1.1.18
Summary: Automated Machine Learning for Humans
Home-page: https://github.com/mljar/mljar-supervised
Author: MLJAR, Sp. z o.o.
Author-email: contact@mljar.com
License: MIT
Keywords: automated machine learning,automl,machine learning,data science,data mining,mljar,random forest,decision tree,xgboost,lightgbm,catboost,neural network,extra trees,linear model,features selection,features engineering
Classifier: Programming Language :: Python
Classifier: Programming Language :: Python :: 3.8
Classifier: Programming Language :: Python :: 3.9
Classifier: Programming Language :: Python :: 3.10
Classifier: Programming Language :: Python :: 3.11
Requires-Python: >=3.8
License-File: LICENSE
